.gitignore
Makefile
README.md
setup.py
./compose/__init__.py
./compose/__main__.py
./compose/operator.py
compose/__init__.py
compose/__main__.py
compose/operator.py
fn_compose.egg-info/PKG-INFO
fn_compose.egg-info/SOURCES.txt
fn_compose.egg-info/dependency_links.txt
fn_compose.egg-info/top_level.txt