Metadata-Version: 1.1
Name: fn-compose
Version: 1.1.3.1
Summary: Make python support function compostion via the matmul operator
Home-page: https://github.com/RyanKung/fn-compose.git
Author: Ryan Kung
Author-email: ryankung@ieee.org
License: MIT
Download-URL: https://github.com/RyanKung/fn-compose/tarball/1.1.2/
Platform: UNKNOWN
Classifier: Development Status :: 4 - Beta
Classifier: Environment :: Console
Classifier: Programming Language :: Python :: 3.5
Classifier: Operating System :: OS Independent
Classifier: Topic :: Software Development
Classifier: Topic :: Software Development :: Libraries :: Python Modules
